{
    "os": "Linux-5.13.0-41-generic-x86_64-with-glibc2.29",
    "python": "3.8.10",
    "heartbeatAt": "2022-05-23T15:05:41.254616",
    "startedAt": "2022-05-23T15:05:40.102462",
    "docker": null,
    "cpu_count": 16,
    "cuda": null,
    "args": null,
    "state": "running",
    "program": "<python with no main file>",
    "git": {
        "remote": "git@github.com:Vanchez23/simple_img_classification_engine.git",
        "commit": "54010ba9cb89cb1318ded5a3ec97feb6557a3036"
    },
    "email": "bukunivan23@gmail.com",
    "root": "/home/vanchez/Projects/ArtLabs",
    "host": "vanchez",
    "username": "vanchez",
    "executable": "/home/vanchez/Projects/ArtLabs/venv2/bin/python3"
}
